uai_uri_interface/__init__.py
uai_uri_interface/py.typed
uai_uri_interface/uri.py
uai_uri_interface-0.1.6.dist-info/LICENSE
uai_uri_interface-0.1.6.dist-info/WHEEL
uai_uri_interface-0.1.6.dist-info/METADATA
uai_uri_interface-0.1.6.dist-info/RECORD
