Metadata-Version: 2.1
Name: uai-uri-interface
Version: 0.1.6
Summary: 
License: MIT
Author: understand.ai
Author-email: postmaster@understand.ai
Requires-Python: >=3.8,<4.0
Classifier: License :: OSI Approved :: MIT License
Classifier: Programming Language :: Python :: 3
Classifier: Programming Language :: Python :: 3.8
Classifier: Programming Language :: Python :: 3.9
Classifier: Programming Language :: Python :: 3.10
Classifier: Programming Language :: Python :: 3.11
